{
    "originalWords": [
        {
            "unicode": "διαπονέω",
            "transliteration": "diaponéō"
        }
    ],
    "description": "to toil through, i.e., (passively) be worried",
    "definition": {
        "to work out laboriously, make complete by labor": {
            "to exert one's self, strive": {},
            "to manage with pains, accomplish with great labor": {},
            "to be troubled, displeased, offended, pained, to be worked up": {}
        }
    },
    "origin": "from g1223 and a derivative of g4192",
    "related": [
        "g1223",
        "g4192"
    ]
}