{
    "originalWords": [
        {
            "unicode": "λυτρόω",
            "transliteration": "lytróō"
        }
    ],
    "description": "to ransom (literally or figuratively)",
    "definition": {
        "to release on receipt of ransom": {},
        "to redeem, liberate by payment of ransom": {
            "to liberate": {},
            "to cause to be released to one's self by payment of a ransom": {},
            "to redeem": {},
            "to deliver: from evils of every kind, internal and external": {}
        }
    },
    "origin": "from g3083",
    "related": [
        "g3083"
    ]
}