{
    "originalWords": [
        {
            "unicode": "Ἀνανίας",
            "transliteration": "Ananías"
        }
    ],
    "description": "ananias, the name of three israelites",
    "literal": "whom jehovah has graciously given",
    "definition": {
        "a certain christian at jerusalem, the husband of sapphira (acts 5:16)": {},
        "a christian at damascus (acts 9:1018)": {},
        "a son of nedebaeus, and high priest of the jews about ad 4759 (acts 23:2) (in the year ad 66, he was slain by the sacarii)": {}
    },
    "origin": "of hebrew origin (h2608)",
    "related": [
        "h2608"
    ]
}