{
    "originalWords": [
        {
            "unicode": "πατάσσω",
            "transliteration": "patássō"
        }
    ],
    "description": "to knock (gently or with a weapon or fatally)",
    "definition": {
        "to strike gently: as a part or a member of the body": {},
        "to stroke, smite: with the sword, to afflict, to visit with evils, etc. as with a deadly disease": {},
        "to smite down, cut down, to kill, slay": {}
    },
    "origin": "probably prolongation from g3817",
    "related": [
        "g3817",
        "g5180"
    ],
    "notes": "compare g5180."
}