{
    "originalWords": [
        {
            "unicode": "πρωτοκλισία",
            "transliteration": "prōtoklisía"
        }
    ],
    "description": "a reclining first (in the place of honor) at the dinner-bed, i.e., preeminence at meals",
    "definition": {
        "the first reclining place, the chief place at table": {},
        "the relative rank of the several places at table varied among the persians, greeks, and romans; and what arrangements the jews had in the time of christ can not be accurately determined": {}
    },
    "origin": "from g4413 and g2828",
    "related": [
        "g2828",
        "g4413"
    ]
}