{
    "originalWords": [
        {
            "unicode": "Σίμων",
            "transliteration": "Símōn"
        }
    ],
    "description": "simon (i.e., shimon), the name of nine israelites",
    "literal": "a rock, stone",
    "definition": {
        "peter was one of the apostles": {},
        "simon called zelotes or the kanaites": {},
        "simon, father of judas who betrayed jesus": {},
        "simon magus, the samaritan wizard": {},
        "simon the tanner, acts 10": {},
        "simon the pharisee, luke 7:4044": {},
        "simon of cyrene who carried the cross of christ": {},
        "simon the cousin of jesus, the son of cleophas": {},
        "simon the leper, so called to distinguish him from others of the same name": {}
    },
    "origin": "of hebrew origin (h8095)",
    "related": [
        "h8095",
        "g4826"
    ],
    "notes": "compare g4826."
}