{
    "originalWords": [
        {
            "unicode": "σκάνδαλον",
            "transliteration": "skándalon"
        }
    ],
    "description": "a trap-stick (bent sapling), i.e., snare (figuratively, cause of displeasure or sin)",
    "definition": {
        "the movable stick or trigger of a trap, a trap stick": {
            "a trap, snare": {},
            "any impediment placed in the way and causing one to stumble or fall, (a stumbling block, occasion of stumbling) i.e., a rock which is a cause of stumbling": {},
            "figuratively applied to jesus christ, whose person and career were so contrary to the expectations of the jews concerning the messiah, that they rejected him and by their obstinacy made shipwreck of their salvation": {}
        },
        "any person or thing by which one is (entrapped) drawn into error or sin": {}
    },
    "origin": "(\"scandal\"); probably from a derivative of g2578",
    "related": [
        "g2578"
    ]
}