{
    "originalWords": "אב",
    "description": "father, in a literal and immediate, or figurative and remote application",
    "definition": {
        "father of an individual": {},
        "of god as father of his people": {},
        "head or founder of a household, group, family, or clan": {},
        "ancestor": {
            "grandfather, forefathers (of a person)": {},
            "of people": {}
        },
        "originator or patron of a class, profession, or art": {},
        "of producer, generator (figuratively)": {},
        "of benevolence and protection (figuratively)": {},
        "term of respect and honor": {},
        "ruler or chief (specifically)": {}
    },
    "origin": "a primitive word",
    "related": [],
    "notes": "compare names in 'abi-'."
}