{
    "originalWords": "בנימין",
    "description": "binjamin, youngest son of jacob; also the tribe descended from him, and its territory",
    "literal": "son of the right hand",
    "definition": {
        "jacob's and rachel's youngest son, joseph's full brother": {},
        "son of bilhan, great-grandson of benjamin": {},
        "a benjamite, one of the sons of harim, in the time of ezra who had taken a strange wife": {},
        "the tribe descended from benjamin, the son of jacob": {}
    },
    "origin": "from h1121 and h3225; son of (the) right hand",
    "related": []
}