{
    "originalWords": "אופיר",
    "description": "ophir, the name of a son of joktan, and of a gold region in the east",
    "literal": "reducing to ashes",
    "definition": {
        "eleventh son of joktan": {},
        "a land or city in southern arabia in solomon's trade route where gold evidently was traded for goods": {},
        "characteristic of fine gold": {},
        "fine gold": {}
    },
    "origin": "or (shortened) ??????; and ??????; of uncertain derivation",
    "related": []
}