{
    "originalWords": "חבא",
    "description": "to secrete",
    "definition": {
        "to withdraw, hide": {
            "(niphal) to hide oneself": {},
            "(pual) to be forced into hiding": {},
            "(hiphil) to hide": {},
            "(hophal) to be hidden": {},
            "(hithpael)": {
                "to hide oneself, draw back": {},
                "to draw together, thicken, harden": {}
            }
        }
    },
    "origin": "a primitive root (compare h2245)",
    "related": []
}