{
    "originalWords": "כפרת",
    "description": "a lid (used only of the cover of the sacred ark)",
    "definition": {
        "mercy-seat, place of atonement": {
            "the golden plate of propitiation on which the high priest sprinkled the seat 7 times on the day of atonement symbolically reconciling jehovah and his chosen people": {
                "the slab of gold on top of the ark of the covenant which measured 2.5 by 1.5 cubits; on it and part of it were the two golden cherubim facing each other whose outstretched wings came together above and constituted the throne of god": {}
            }
        }
    },
    "origin": "from h3722",
    "related": []
}