{
    "originalWords": "מצפה",
    "description": "mitspah, the name of two places in palestine",
    "literal": "watchtower",
    "definition": {
        "a place in gilead north of jabbok and location of laban's cairn": {},
        "a place in gilead south of jabbok; site unknown": {},
        "a place near mount hermon": {},
        "an old sacred place in benjamin": {}
    },
    "origin": "feminine of h4708",
    "related": [],
    "notes": "this seems rather to be only an orthographic variation of h4708 when 'in pause'."
}