{
    "originalWords": "מקום",
    "description": "properly, a standing, i.e., a spot; but used widely of a locality (general or specific); also (figuratively) of a condition (of body or mind)",
    "definition": {
        "standing place, place": {
            "standing place, station, post, office": {},
            "place, place of human abode": {},
            "city, land, region": {},
            "place, locality, spot": {},
            "space, room, distance": {},
            "region, quarter, direction": {},
            "give place to, instead of": {}
        }
    },
    "origin": "or ?????; also (feminine) ????????; or ???????; from h6965",
    "related": []
}