{
    "originalWords": "סקל",
    "description": "properly, to be weighty; but used only in the sense of lapidation or its contrary (as if a delapidation)",
    "definition": {
        "to stone (to death), put to death by stoning": {
            "(qal) to pelt with stones, stone to death": {},
            "(niphal) to be stoned to death": {},
            "(piel)": {
                "to stone, pelt with stones": {},
                "to free from stones (of vineyard, highway)": {}
            },
            "(pual) to be stoned to death": {}
        }
    },
    "origin": "a primitive root",
    "related": []
}