{
    "originalWords": "ראשון",
    "description": "first, in place, time or rank (as adjective or noun)",
    "definition": {
        "(adj) first, primary, former": {
            "former (of time)": {
                "ancestors": {},
                "former things": {}
            },
            "foremost (of location)": {},
            "first (in time)": {},
            "first, chief (in degree)": {}
        },
        "(adv) first, before, formerly, at first": {}
    },
    "origin": "or ???????; from h7221",
    "related": []
}