{
    "originalWords": "שכח",
    "description": "to mislay, i.e., to be oblivious of, from want of memory or attention",
    "definition": {
        "to forget, ignore, wither": {
            "(qal)": {
                "to forget": {},
                "to cease to care": {}
            },
            "(niphal) to be forgotten": {},
            "(piel) to cause to forget": {},
            "(hiphil) to make or cause to forget": {},
            "(hithpael) to be forgotten": {}
        }
    },
    "origin": "or ???????; a primitive root",
    "related": []
}