{
    "originalWords": "שמש",
    "description": "the sun; by implication, the east; figuratively, a ray, i.e., (architectural) a notched battlement",
    "definition": {
        "sun": {
            "sun": {},
            "sunrise, sun-rising, east, sun-setting, west (of direction)": {},
            "sun (as object of illicit worship)": {},
            "openly, publicly (in other phrases)": {},
            "pinnacles, battlements, shields (as glittering or shining)": {}
        }
    },
    "origin": "from an unused root meaning to be brilliant",
    "related": [
        "h1053"
    ]
}